{
  "title": "Sodium diacetate",
  "eNumber": "E262II",
  "synonyms": [
    "E262ii",
    "Sodium diacetate"
  ],
  "functions": [
    "preservative",
    "sequestrant"
  ],
  "description": "Sodium acetate, CH3COONa, also abbreviated NaOAc, is the sodium salt of acetic acid. This colorless deliquescent salt has a wide range of uses.",
  "wikipedia": "https://en.wikipedia.org/wiki/Sodium_diacetate",
  "wikidata": "Q409655",
  "searchVolume": 1600,
  "searchRank": 198,
  "searchSparkline": [
    2178,
    2685,
    2145,
    2560,
    880,
    1036,
    1170,
    1233,
    1658,
    1459
  ]
}
