{
  "title": "Brilliant blue FCF",
  "eNumber": "E133",
  "synonyms": [
    "E133",
    "Brilliant blue FCF",
    "FD&C Blue 1",
    "FD and C Blue 1",
    "Blue 1",
    "fd&c blue no. 1",
    "Blue 1 lake"
  ],
  "functions": [
    "colour"
  ],
  "description": "Brilliant Blue FCF -Blue 1- is an organic compound classified as a triarylmethane dye and a blue azo dye, reflecting its chemical structure. Known under various commercial names, it is a colorant for foods and other substances. It is denoted by E number E133 and has a  color index of 42090. It has the appearance of a blue powder. It is soluble in water, and the solution has a maximum absorption at about 628 nanometers.",
  "wikipedia": "https://en.wikipedia.org/wiki/Brilliant_Blue_FCF",
  "wikidata": "Q420093",
  "searchVolume": 800,
  "searchRank": 219,
  "searchSparkline": [
    378,
    665,
    1086,
    1438,
    324,
    296,
    335,
    457,
    690,
    795
  ]
}
