{
  "title": "Magnesium carbonate",
  "eNumber": "E504I",
  "synonyms": [
    "E504i",
    "Magnesium carbonate"
  ],
  "functions": [
    "carrier"
  ],
  "description": "Magnesium carbonate, MgCO3 -archaic name magnesia alba-, is an inorganic salt that is a white solid. Several hydrated and basic forms of magnesium carbonate also exist as minerals.",
  "wikipedia": "https://en.wikipedia.org/wiki/Magnesium_carbonate",
  "wikidata": "Q407931",
  "searchVolume": 12000,
  "searchRank": 106,
  "searchSparkline": [
    10573,
    11062,
    11126,
    10026,
    10082,
    9618,
    11683,
    12908,
    12489,
    11730
  ]
}
