{
  "keyword": "Brilliant blue FCF",
  "country": "us",
  "fetchedAt": "2025-09-27T02:57:31.019Z",
  "metrics": [
    {
      "date": "2016-01-01T00:00:00Z",
      "volume": 519
    },
    {
      "date": "2016-02-01T00:00:00Z",
      "volume": 519
    },
    {
      "date": "2016-03-01T00:00:00Z",
      "volume": 259
    },
    {
      "date": "2016-04-01T00:00:00Z",
      "volume": 454
    },
    {
      "date": "2016-05-01T00:00:00Z",
      "volume": 454
    },
    {
      "date": "2016-06-01T00:00:00Z",
      "volume": 584
    },
    {
      "date": "2016-07-01T00:00:00Z",
      "volume": 259
    },
    {
      "date": "2016-08-01T00:00:00Z",
      "volume": 195
    },
    {
      "date": "2016-09-01T00:00:00Z",
      "volume": 195
    },
    {
      "date": "2016-10-01T00:00:00Z",
      "volume": 195
    },
    {
      "date": "2016-11-01T00:00:00Z",
      "volume": 259
    },
    {
      "date": "2016-12-01T00:00:00Z",
      "volume": 648
    },
    {
      "date": "2017-01-01T00:00:00Z",
      "volume": 1037
    },
    {
      "date": "2017-02-01T00:00:00Z",
      "volume": 1362
    },
    {
      "date": "2017-03-01T00:00:00Z",
      "volume": 973
    },
    {
      "date": "2017-04-01T00:00:00Z",
      "volume": 649
    },
    {
      "date": "2017-05-01T00:00:00Z",
      "volume": 260
    },
    {
      "date": "2017-06-01T00:00:00Z",
      "volume": 195
    },
    {
      "date": "2017-07-01T00:00:00Z",
      "volume": 195
    },
    {
      "date": "2017-08-01T00:00:00Z",
      "volume": 584
    },
    {
      "date": "2017-09-01T00:00:00Z",
      "volume": 778
    },
    {
      "date": "2017-10-01T00:00:00Z",
      "volume": 908
    },
    {
      "date": "2017-11-01T00:00:00Z",
      "volume": 454
    },
    {
      "date": "2017-12-01T00:00:00Z",
      "volume": 584
    },
    {
      "date": "2018-01-01T00:00:00Z",
      "volume": 778
    },
    {
      "date": "2018-02-01T00:00:00Z",
      "volume": 1167
    },
    {
      "date": "2018-03-01T00:00:00Z",
      "volume": 1167
    },
    {
      "date": "2018-04-01T00:00:00Z",
      "volume": 1556
    },
    {
      "date": "2018-05-01T00:00:00Z",
      "volume": 1686
    },
    {
      "date": "2018-06-01T00:00:00Z",
      "volume": 1362
    },
    {
      "date": "2018-07-01T00:00:00Z",
      "volume": 649
    },
    {
      "date": "2018-08-01T00:00:00Z",
      "volume": 325
    },
    {
      "date": "2018-09-01T00:00:00Z",
      "volume": 649
    },
    {
      "date": "2018-10-01T00:00:00Z",
      "volume": 973
    },
    {
      "date": "2018-11-01T00:00:00Z",
      "volume": 973
    },
    {
      "date": "2018-12-01T00:00:00Z",
      "volume": 1751
    },
    {
      "date": "2019-01-01T00:00:00Z",
      "volume": 2205
    },
    {
      "date": "2019-02-01T00:00:00Z",
      "volume": 2399
    },
    {
      "date": "2019-03-01T00:00:00Z",
      "volume": 1751
    },
    {
      "date": "2019-04-01T00:00:00Z",
      "volume": 1362
    },
    {
      "date": "2019-05-01T00:00:00Z",
      "volume": 1038
    },
    {
      "date": "2019-06-01T00:00:00Z",
      "volume": 714
    },
    {
      "date": "2019-07-01T00:00:00Z",
      "volume": 908
    },
    {
      "date": "2019-08-01T00:00:00Z",
      "volume": 2010
    },
    {
      "date": "2019-09-01T00:00:00Z",
      "volume": 2529
    },
    {
      "date": "2019-10-01T00:00:00Z",
      "volume": 972
    },
    {
      "date": "2019-11-01T00:00:00Z",
      "volume": 712
    },
    {
      "date": "2019-12-01T00:00:00Z",
      "volume": 654
    },
    {
      "date": "2020-01-01T00:00:00Z",
      "volume": 490
    },
    {
      "date": "2020-02-01T00:00:00Z",
      "volume": 557
    },
    {
      "date": "2020-03-01T00:00:00Z",
      "volume": 402
    },
    {
      "date": "2020-04-01T00:00:00Z",
      "volume": 329
    },
    {
      "date": "2020-05-01T00:00:00Z",
      "volume": 218
    },
    {
      "date": "2020-06-01T00:00:00Z",
      "volume": 178
    },
    {
      "date": "2020-07-01T00:00:00Z",
      "volume": 330
    },
    {
      "date": "2020-08-01T00:00:00Z",
      "volume": 330
    },
    {
      "date": "2020-09-01T00:00:00Z",
      "volume": 333
    },
    {
      "date": "2020-10-01T00:00:00Z",
      "volume": 373
    },
    {
      "date": "2020-11-01T00:00:00Z",
      "volume": 187
    },
    {
      "date": "2020-12-01T00:00:00Z",
      "volume": 162
    },
    {
      "date": "2021-01-01T00:00:00Z",
      "volume": 197
    },
    {
      "date": "2021-02-01T00:00:00Z",
      "volume": 374
    },
    {
      "date": "2021-03-01T00:00:00Z",
      "volume": 303
    },
    {
      "date": "2021-04-01T00:00:00Z",
      "volume": 303
    },
    {
      "date": "2021-05-01T00:00:00Z",
      "volume": 199
    },
    {
      "date": "2021-06-01T00:00:00Z",
      "volume": 249
    },
    {
      "date": "2021-07-01T00:00:00Z",
      "volume": 198
    },
    {
      "date": "2021-08-01T00:00:00Z",
      "volume": 208
    },
    {
      "date": "2021-09-01T00:00:00Z",
      "volume": 501
    },
    {
      "date": "2021-10-01T00:00:00Z",
      "volume": 472
    },
    {
      "date": "2021-11-01T00:00:00Z",
      "volume": 292
    },
    {
      "date": "2021-12-01T00:00:00Z",
      "volume": 251
    },
    {
      "date": "2022-01-01T00:00:00Z",
      "volume": 306
    },
    {
      "date": "2022-02-01T00:00:00Z",
      "volume": 385
    },
    {
      "date": "2022-03-01T00:00:00Z",
      "volume": 235
    },
    {
      "date": "2022-04-01T00:00:00Z",
      "volume": 692
    },
    {
      "date": "2022-05-01T00:00:00Z",
      "volume": 206
    },
    {
      "date": "2022-06-01T00:00:00Z",
      "volume": 247
    },
    {
      "date": "2022-07-01T00:00:00Z",
      "volume": 199
    },
    {
      "date": "2022-08-01T00:00:00Z",
      "volume": 304
    },
    {
      "date": "2022-09-01T00:00:00Z",
      "volume": 397
    },
    {
      "date": "2022-10-01T00:00:00Z",
      "volume": 590
    },
    {
      "date": "2022-11-01T00:00:00Z",
      "volume": 252
    },
    {
      "date": "2022-12-01T00:00:00Z",
      "volume": 205
    },
    {
      "date": "2023-01-01T00:00:00Z",
      "volume": 393
    },
    {
      "date": "2023-02-01T00:00:00Z",
      "volume": 385
    },
    {
      "date": "2023-03-01T00:00:00Z",
      "volume": 388
    },
    {
      "date": "2023-04-01T00:00:00Z",
      "volume": 632
    },
    {
      "date": "2023-05-01T00:00:00Z",
      "volume": 420
    },
    {
      "date": "2023-06-01T00:00:00Z",
      "volume": 363
    },
    {
      "date": "2023-07-01T00:00:00Z",
      "volume": 378
    },
    {
      "date": "2023-08-01T00:00:00Z",
      "volume": 405
    },
    {
      "date": "2023-09-01T00:00:00Z",
      "volume": 513
    },
    {
      "date": "2023-10-01T00:00:00Z",
      "volume": 545
    },
    {
      "date": "2023-11-01T00:00:00Z",
      "volume": 514
    },
    {
      "date": "2023-12-01T00:00:00Z",
      "volume": 553
    },
    {
      "date": "2024-01-01T00:00:00Z",
      "volume": 670
    },
    {
      "date": "2024-02-01T00:00:00Z",
      "volume": 756
    },
    {
      "date": "2024-03-01T00:00:00Z",
      "volume": 657
    },
    {
      "date": "2024-04-01T00:00:00Z",
      "volume": 957
    },
    {
      "date": "2024-05-01T00:00:00Z",
      "volume": 543
    },
    {
      "date": "2024-06-01T00:00:00Z",
      "volume": 627
    },
    {
      "date": "2024-07-01T00:00:00Z",
      "volume": 634
    },
    {
      "date": "2024-08-01T00:00:00Z",
      "volume": 700
    },
    {
      "date": "2024-09-01T00:00:00Z",
      "volume": 583
    },
    {
      "date": "2024-10-01T00:00:00Z",
      "volume": 725
    },
    {
      "date": "2024-11-01T00:00:00Z",
      "volume": 779
    },
    {
      "date": "2024-12-01T00:00:00Z",
      "volume": 651
    },
    {
      "date": "2025-01-01T00:00:00Z",
      "volume": 761
    },
    {
      "date": "2025-02-01T00:00:00Z",
      "volume": 748
    },
    {
      "date": "2025-03-01T00:00:00Z",
      "volume": 762
    },
    {
      "date": "2025-04-01T00:00:00Z",
      "volume": 1150
    },
    {
      "date": "2025-05-01T00:00:00Z",
      "volume": 757
    },
    {
      "date": "2025-06-01T00:00:00Z",
      "volume": 750
    },
    {
      "date": "2025-07-01T00:00:00Z",
      "volume": 672
    },
    {
      "date": "2025-08-01T00:00:00Z",
      "volume": 814
    },
    {
      "date": "2025-09-01T00:00:00Z",
      "volume": 954
    },
    {
      "date": "2025-10-01T00:00:00Z",
      "volume": 830
    },
    {
      "date": "2025-11-01T00:00:00Z",
      "volume": 634
    },
    {
      "date": "2025-12-01T00:00:00Z",
      "volume": 702
    }
  ]
}
