{
  "keyword": "Sodium propionate",
  "country": "us",
  "fetchedAt": "2025-09-27T03:00:41.590Z",
  "metrics": [
    {
      "date": "2016-01-01T00:00:00Z",
      "volume": 1621
    },
    {
      "date": "2016-02-01T00:00:00Z",
      "volume": 2075
    },
    {
      "date": "2016-03-01T00:00:00Z",
      "volume": 1945
    },
    {
      "date": "2016-04-01T00:00:00Z",
      "volume": 1491
    },
    {
      "date": "2016-05-01T00:00:00Z",
      "volume": 454
    },
    {
      "date": "2016-06-01T00:00:00Z",
      "volume": 324
    },
    {
      "date": "2016-07-01T00:00:00Z",
      "volume": 584
    },
    {
      "date": "2016-08-01T00:00:00Z",
      "volume": 973
    },
    {
      "date": "2016-09-01T00:00:00Z",
      "volume": 973
    },
    {
      "date": "2016-10-01T00:00:00Z",
      "volume": 1751
    },
    {
      "date": "2016-11-01T00:00:00Z",
      "volume": 1815
    },
    {
      "date": "2016-12-01T00:00:00Z",
      "volume": 2140
    },
    {
      "date": "2017-01-01T00:00:00Z",
      "volume": 1686
    },
    {
      "date": "2017-02-01T00:00:00Z",
      "volume": 1881
    },
    {
      "date": "2017-03-01T00:00:00Z",
      "volume": 1945
    },
    {
      "date": "2017-04-01T00:00:00Z",
      "volume": 1491
    },
    {
      "date": "2017-05-01T00:00:00Z",
      "volume": 1426
    },
    {
      "date": "2017-06-01T00:00:00Z",
      "volume": 1232
    },
    {
      "date": "2017-07-01T00:00:00Z",
      "volume": 1556
    },
    {
      "date": "2017-08-01T00:00:00Z",
      "volume": 1232
    },
    {
      "date": "2017-09-01T00:00:00Z",
      "volume": 1232
    },
    {
      "date": "2017-10-01T00:00:00Z",
      "volume": 1038
    },
    {
      "date": "2017-11-01T00:00:00Z",
      "volume": 1167
    },
    {
      "date": "2017-12-01T00:00:00Z",
      "volume": 1362
    },
    {
      "date": "2018-01-01T00:00:00Z",
      "volume": 1427
    },
    {
      "date": "2018-02-01T00:00:00Z",
      "volume": 1621
    },
    {
      "date": "2018-03-01T00:00:00Z",
      "volume": 1362
    },
    {
      "date": "2018-04-01T00:00:00Z",
      "volume": 1102
    },
    {
      "date": "2018-05-01T00:00:00Z",
      "volume": 778
    },
    {
      "date": "2018-06-01T00:00:00Z",
      "volume": 389
    },
    {
      "date": "2018-07-01T00:00:00Z",
      "volume": 389
    },
    {
      "date": "2018-08-01T00:00:00Z",
      "volume": 454
    },
    {
      "date": "2018-09-01T00:00:00Z",
      "volume": 908
    },
    {
      "date": "2018-10-01T00:00:00Z",
      "volume": 1427
    },
    {
      "date": "2018-11-01T00:00:00Z",
      "volume": 1103
    },
    {
      "date": "2018-12-01T00:00:00Z",
      "volume": 1492
    },
    {
      "date": "2019-01-01T00:00:00Z",
      "volume": 1103
    },
    {
      "date": "2019-02-01T00:00:00Z",
      "volume": 2205
    },
    {
      "date": "2019-03-01T00:00:00Z",
      "volume": 2658
    },
    {
      "date": "2019-04-01T00:00:00Z",
      "volume": 2658
    },
    {
      "date": "2019-05-01T00:00:00Z",
      "volume": 1686
    },
    {
      "date": "2019-06-01T00:00:00Z",
      "volume": 454
    },
    {
      "date": "2019-07-01T00:00:00Z",
      "volume": 1167
    },
    {
      "date": "2019-08-01T00:00:00Z",
      "volume": 1038
    },
    {
      "date": "2019-09-01T00:00:00Z",
      "volume": 673
    },
    {
      "date": "2019-10-01T00:00:00Z",
      "volume": 577
    },
    {
      "date": "2019-11-01T00:00:00Z",
      "volume": 694
    },
    {
      "date": "2019-12-01T00:00:00Z",
      "volume": 668
    },
    {
      "date": "2020-01-01T00:00:00Z",
      "volume": 487
    },
    {
      "date": "2020-02-01T00:00:00Z",
      "volume": 644
    },
    {
      "date": "2020-03-01T00:00:00Z",
      "volume": 642
    },
    {
      "date": "2020-04-01T00:00:00Z",
      "volume": 951
    },
    {
      "date": "2020-05-01T00:00:00Z",
      "volume": 634
    },
    {
      "date": "2020-06-01T00:00:00Z",
      "volume": 488
    },
    {
      "date": "2020-07-01T00:00:00Z",
      "volume": 512
    },
    {
      "date": "2020-08-01T00:00:00Z",
      "volume": 518
    },
    {
      "date": "2020-09-01T00:00:00Z",
      "volume": 717
    },
    {
      "date": "2020-10-01T00:00:00Z",
      "volume": 717
    },
    {
      "date": "2020-11-01T00:00:00Z",
      "volume": 611
    },
    {
      "date": "2020-12-01T00:00:00Z",
      "volume": 591
    },
    {
      "date": "2021-01-01T00:00:00Z",
      "volume": 684
    },
    {
      "date": "2021-02-01T00:00:00Z",
      "volume": 1010
    },
    {
      "date": "2021-03-01T00:00:00Z",
      "volume": 1462
    },
    {
      "date": "2021-04-01T00:00:00Z",
      "volume": 1814
    },
    {
      "date": "2021-05-01T00:00:00Z",
      "volume": 876
    },
    {
      "date": "2021-06-01T00:00:00Z",
      "volume": 617
    },
    {
      "date": "2021-07-01T00:00:00Z",
      "volume": 693
    },
    {
      "date": "2021-08-01T00:00:00Z",
      "volume": 614
    },
    {
      "date": "2021-09-01T00:00:00Z",
      "volume": 727
    },
    {
      "date": "2021-10-01T00:00:00Z",
      "volume": 879
    },
    {
      "date": "2021-11-01T00:00:00Z",
      "volume": 877
    },
    {
      "date": "2021-12-01T00:00:00Z",
      "volume": 601
    },
    {
      "date": "2022-01-01T00:00:00Z",
      "volume": 626
    },
    {
      "date": "2022-02-01T00:00:00Z",
      "volume": 884
    },
    {
      "date": "2022-03-01T00:00:00Z",
      "volume": 1297
    },
    {
      "date": "2022-04-01T00:00:00Z",
      "volume": 1237
    },
    {
      "date": "2022-05-01T00:00:00Z",
      "volume": 701
    },
    {
      "date": "2022-06-01T00:00:00Z",
      "volume": 611
    },
    {
      "date": "2022-07-01T00:00:00Z",
      "volume": 620
    },
    {
      "date": "2022-08-01T00:00:00Z",
      "volume": 623
    },
    {
      "date": "2022-09-01T00:00:00Z",
      "volume": 716
    },
    {
      "date": "2022-10-01T00:00:00Z",
      "volume": 893
    },
    {
      "date": "2022-11-01T00:00:00Z",
      "volume": 862
    },
    {
      "date": "2022-12-01T00:00:00Z",
      "volume": 597
    },
    {
      "date": "2023-01-01T00:00:00Z",
      "volume": 702
    },
    {
      "date": "2023-02-01T00:00:00Z",
      "volume": 892
    },
    {
      "date": "2023-03-01T00:00:00Z",
      "volume": 1252
    },
    {
      "date": "2023-04-01T00:00:00Z",
      "volume": 1251
    },
    {
      "date": "2023-05-01T00:00:00Z",
      "volume": 873
    },
    {
      "date": "2023-06-01T00:00:00Z",
      "volume": 703
    },
    {
      "date": "2023-07-01T00:00:00Z",
      "volume": 659
    },
    {
      "date": "2023-08-01T00:00:00Z",
      "volume": 665
    },
    {
      "date": "2023-09-01T00:00:00Z",
      "volume": 678
    },
    {
      "date": "2023-10-01T00:00:00Z",
      "volume": 1031
    },
    {
      "date": "2023-11-01T00:00:00Z",
      "volume": 1056
    },
    {
      "date": "2023-12-01T00:00:00Z",
      "volume": 672
    },
    {
      "date": "2024-01-01T00:00:00Z",
      "volume": 868
    },
    {
      "date": "2024-02-01T00:00:00Z",
      "volume": 1032
    },
    {
      "date": "2024-03-01T00:00:00Z",
      "volume": 1554
    },
    {
      "date": "2024-04-01T00:00:00Z",
      "volume": 1525
    },
    {
      "date": "2024-05-01T00:00:00Z",
      "volume": 849
    },
    {
      "date": "2024-06-01T00:00:00Z",
      "volume": 863
    },
    {
      "date": "2024-07-01T00:00:00Z",
      "volume": 846
    },
    {
      "date": "2024-08-01T00:00:00Z",
      "volume": 698
    },
    {
      "date": "2024-09-01T00:00:00Z",
      "volume": 903
    },
    {
      "date": "2024-10-01T00:00:00Z",
      "volume": 1070
    },
    {
      "date": "2024-11-01T00:00:00Z",
      "volume": 1062
    },
    {
      "date": "2024-12-01T00:00:00Z",
      "volume": 868
    },
    {
      "date": "2025-01-01T00:00:00Z",
      "volume": 835
    },
    {
      "date": "2025-02-01T00:00:00Z",
      "volume": 1046
    },
    {
      "date": "2025-03-01T00:00:00Z",
      "volume": 1241
    },
    {
      "date": "2025-04-01T00:00:00Z",
      "volume": 1539
    },
    {
      "date": "2025-05-01T00:00:00Z",
      "volume": 885
    },
    {
      "date": "2025-06-01T00:00:00Z",
      "volume": 692
    },
    {
      "date": "2025-07-01T00:00:00Z",
      "volume": 722
    },
    {
      "date": "2025-08-01T00:00:00Z",
      "volume": 681
    },
    {
      "date": "2025-09-01T00:00:00Z",
      "volume": 801
    },
    {
      "date": "2025-10-01T00:00:00Z",
      "volume": 1019
    },
    {
      "date": "2025-11-01T00:00:00Z",
      "volume": 977
    },
    {
      "date": "2025-12-01T00:00:00Z",
      "volume": 939
    }
  ]
}
