{
  "keyword": "Magnesium stearate",
  "country": "us",
  "fetchedAt": "2025-09-27T02:59:17.492Z",
  "metrics": [
    {
      "date": "2016-01-01T00:00:00Z",
      "volume": 15427
    },
    {
      "date": "2016-02-01T00:00:00Z",
      "volume": 16802
    },
    {
      "date": "2016-03-01T00:00:00Z",
      "volume": 19870
    },
    {
      "date": "2016-04-01T00:00:00Z",
      "volume": 18273
    },
    {
      "date": "2016-05-01T00:00:00Z",
      "volume": 18407
    },
    {
      "date": "2016-06-01T00:00:00Z",
      "volume": 16037
    },
    {
      "date": "2016-07-01T00:00:00Z",
      "volume": 15652
    },
    {
      "date": "2016-08-01T00:00:00Z",
      "volume": 15596
    },
    {
      "date": "2016-09-01T00:00:00Z",
      "volume": 15319
    },
    {
      "date": "2016-10-01T00:00:00Z",
      "volume": 15613
    },
    {
      "date": "2016-11-01T00:00:00Z",
      "volume": 15661
    },
    {
      "date": "2016-12-01T00:00:00Z",
      "volume": 14029
    },
    {
      "date": "2017-01-01T00:00:00Z",
      "volume": 16435
    },
    {
      "date": "2017-02-01T00:00:00Z",
      "volume": 18127
    },
    {
      "date": "2017-03-01T00:00:00Z",
      "volume": 18416
    },
    {
      "date": "2017-04-01T00:00:00Z",
      "volume": 17118
    },
    {
      "date": "2017-05-01T00:00:00Z",
      "volume": 17226
    },
    {
      "date": "2017-06-01T00:00:00Z",
      "volume": 17222
    },
    {
      "date": "2017-07-01T00:00:00Z",
      "volume": 16526
    },
    {
      "date": "2017-08-01T00:00:00Z",
      "volume": 17296
    },
    {
      "date": "2017-09-01T00:00:00Z",
      "volume": 15994
    },
    {
      "date": "2017-10-01T00:00:00Z",
      "volume": 14575
    },
    {
      "date": "2017-11-01T00:00:00Z",
      "volume": 17440
    },
    {
      "date": "2017-12-01T00:00:00Z",
      "volume": 15470
    },
    {
      "date": "2018-01-01T00:00:00Z",
      "volume": 18949
    },
    {
      "date": "2018-02-01T00:00:00Z",
      "volume": 19551
    },
    {
      "date": "2018-03-01T00:00:00Z",
      "volume": 19434
    },
    {
      "date": "2018-04-01T00:00:00Z",
      "volume": 18123
    },
    {
      "date": "2018-05-01T00:00:00Z",
      "volume": 17512
    },
    {
      "date": "2018-06-01T00:00:00Z",
      "volume": 15950
    },
    {
      "date": "2018-07-01T00:00:00Z",
      "volume": 18244
    },
    {
      "date": "2018-08-01T00:00:00Z",
      "volume": 16962
    },
    {
      "date": "2018-09-01T00:00:00Z",
      "volume": 16949
    },
    {
      "date": "2018-10-01T00:00:00Z",
      "volume": 15275
    },
    {
      "date": "2018-11-01T00:00:00Z",
      "volume": 14367
    },
    {
      "date": "2018-12-01T00:00:00Z",
      "volume": 15820
    },
    {
      "date": "2019-01-01T00:00:00Z",
      "volume": 18482
    },
    {
      "date": "2019-02-01T00:00:00Z",
      "volume": 17465
    },
    {
      "date": "2019-03-01T00:00:00Z",
      "volume": 18235
    },
    {
      "date": "2019-04-01T00:00:00Z",
      "volume": 17283
    },
    {
      "date": "2019-05-01T00:00:00Z",
      "volume": 16669
    },
    {
      "date": "2019-06-01T00:00:00Z",
      "volume": 16491
    },
    {
      "date": "2019-07-01T00:00:00Z",
      "volume": 16755
    },
    {
      "date": "2019-08-01T00:00:00Z",
      "volume": 16327
    },
    {
      "date": "2019-09-01T00:00:00Z",
      "volume": 14532
    },
    {
      "date": "2019-10-01T00:00:00Z",
      "volume": 14978
    },
    {
      "date": "2019-11-01T00:00:00Z",
      "volume": 14769
    },
    {
      "date": "2019-12-01T00:00:00Z",
      "volume": 14122
    },
    {
      "date": "2020-01-01T00:00:00Z",
      "volume": 17764
    },
    {
      "date": "2020-02-01T00:00:00Z",
      "volume": 18560
    },
    {
      "date": "2020-03-01T00:00:00Z",
      "volume": 16380
    },
    {
      "date": "2020-04-01T00:00:00Z",
      "volume": 15374
    },
    {
      "date": "2020-05-01T00:00:00Z",
      "volume": 23046
    },
    {
      "date": "2020-06-01T00:00:00Z",
      "volume": 16799
    },
    {
      "date": "2020-07-01T00:00:00Z",
      "volume": 17041
    },
    {
      "date": "2020-08-01T00:00:00Z",
      "volume": 15301
    },
    {
      "date": "2020-09-01T00:00:00Z",
      "volume": 14556
    },
    {
      "date": "2020-10-01T00:00:00Z",
      "volume": 15219
    },
    {
      "date": "2020-11-01T00:00:00Z",
      "volume": 12579
    },
    {
      "date": "2020-12-01T00:00:00Z",
      "volume": 13033
    },
    {
      "date": "2021-01-01T00:00:00Z",
      "volume": 17310
    },
    {
      "date": "2021-02-01T00:00:00Z",
      "volume": 17942
    },
    {
      "date": "2021-03-01T00:00:00Z",
      "volume": 16665
    },
    {
      "date": "2021-04-01T00:00:00Z",
      "volume": 15753
    },
    {
      "date": "2021-05-01T00:00:00Z",
      "volume": 15227
    },
    {
      "date": "2021-06-01T00:00:00Z",
      "volume": 14557
    },
    {
      "date": "2021-07-01T00:00:00Z",
      "volume": 16199
    },
    {
      "date": "2021-08-01T00:00:00Z",
      "volume": 17076
    },
    {
      "date": "2021-09-01T00:00:00Z",
      "volume": 18192
    },
    {
      "date": "2021-10-01T00:00:00Z",
      "volume": 16836
    },
    {
      "date": "2021-11-01T00:00:00Z",
      "volume": 13915
    },
    {
      "date": "2021-12-01T00:00:00Z",
      "volume": 12597
    },
    {
      "date": "2022-01-01T00:00:00Z",
      "volume": 23553
    },
    {
      "date": "2022-02-01T00:00:00Z",
      "volume": 20715
    },
    {
      "date": "2022-03-01T00:00:00Z",
      "volume": 20328
    },
    {
      "date": "2022-04-01T00:00:00Z",
      "volume": 19414
    },
    {
      "date": "2022-05-01T00:00:00Z",
      "volume": 18534
    },
    {
      "date": "2022-06-01T00:00:00Z",
      "volume": 16494
    },
    {
      "date": "2022-07-01T00:00:00Z",
      "volume": 18087
    },
    {
      "date": "2022-08-01T00:00:00Z",
      "volume": 17699
    },
    {
      "date": "2022-09-01T00:00:00Z",
      "volume": 16303
    },
    {
      "date": "2022-10-01T00:00:00Z",
      "volume": 16792
    },
    {
      "date": "2022-11-01T00:00:00Z",
      "volume": 15226
    },
    {
      "date": "2022-12-01T00:00:00Z",
      "volume": 17265
    },
    {
      "date": "2023-01-01T00:00:00Z",
      "volume": 23577
    },
    {
      "date": "2023-02-01T00:00:00Z",
      "volume": 26163
    },
    {
      "date": "2023-03-01T00:00:00Z",
      "volume": 26290
    },
    {
      "date": "2023-04-01T00:00:00Z",
      "volume": 24199
    },
    {
      "date": "2023-05-01T00:00:00Z",
      "volume": 22870
    },
    {
      "date": "2023-06-01T00:00:00Z",
      "volume": 22586
    },
    {
      "date": "2023-07-01T00:00:00Z",
      "volume": 22359
    },
    {
      "date": "2023-08-01T00:00:00Z",
      "volume": 23982
    },
    {
      "date": "2023-09-01T00:00:00Z",
      "volume": 24214
    },
    {
      "date": "2023-10-01T00:00:00Z",
      "volume": 23962
    },
    {
      "date": "2023-11-01T00:00:00Z",
      "volume": 21679
    },
    {
      "date": "2023-12-01T00:00:00Z",
      "volume": 19713
    },
    {
      "date": "2024-01-01T00:00:00Z",
      "volume": 26280
    },
    {
      "date": "2024-02-01T00:00:00Z",
      "volume": 26429
    },
    {
      "date": "2024-03-01T00:00:00Z",
      "volume": 25394
    },
    {
      "date": "2024-04-01T00:00:00Z",
      "volume": 22927
    },
    {
      "date": "2024-05-01T00:00:00Z",
      "volume": 23346
    },
    {
      "date": "2024-06-01T00:00:00Z",
      "volume": 22230
    },
    {
      "date": "2024-07-01T00:00:00Z",
      "volume": 21600
    },
    {
      "date": "2024-08-01T00:00:00Z",
      "volume": 22494
    },
    {
      "date": "2024-09-01T00:00:00Z",
      "volume": 22933
    },
    {
      "date": "2024-10-01T00:00:00Z",
      "volume": 22951
    },
    {
      "date": "2024-11-01T00:00:00Z",
      "volume": 21783
    },
    {
      "date": "2024-12-01T00:00:00Z",
      "volume": 22879
    },
    {
      "date": "2025-01-01T00:00:00Z",
      "volume": 27425
    },
    {
      "date": "2025-02-01T00:00:00Z",
      "volume": 26434
    },
    {
      "date": "2025-03-01T00:00:00Z",
      "volume": 24942
    },
    {
      "date": "2025-04-01T00:00:00Z",
      "volume": 24253
    },
    {
      "date": "2025-05-01T00:00:00Z",
      "volume": 22713
    },
    {
      "date": "2025-06-01T00:00:00Z",
      "volume": 23692
    },
    {
      "date": "2025-07-01T00:00:00Z",
      "volume": 23011
    },
    {
      "date": "2025-08-01T00:00:00Z",
      "volume": 23920
    },
    {
      "date": "2025-09-01T00:00:00Z",
      "volume": 23486
    },
    {
      "date": "2025-10-01T00:00:00Z",
      "volume": 23157
    },
    {
      "date": "2025-11-01T00:00:00Z",
      "volume": 22419
    },
    {
      "date": "2025-12-01T00:00:00Z",
      "volume": 21862
    }
  ]
}
