{
  "keyword": "Pectins",
  "country": "us",
  "fetchedAt": "2025-09-27T02:59:44.802Z",
  "metrics": [
    {
      "date": "2016-01-01T00:00:00Z",
      "volume": 454
    },
    {
      "date": "2016-02-01T00:00:00Z",
      "volume": 454
    },
    {
      "date": "2016-03-01T00:00:00Z",
      "volume": 454
    },
    {
      "date": "2016-04-01T00:00:00Z",
      "volume": 389
    },
    {
      "date": "2016-05-01T00:00:00Z",
      "volume": 389
    },
    {
      "date": "2016-06-01T00:00:00Z",
      "volume": 519
    },
    {
      "date": "2016-07-01T00:00:00Z",
      "volume": 519
    },
    {
      "date": "2016-08-01T00:00:00Z",
      "volume": 713
    },
    {
      "date": "2016-09-01T00:00:00Z",
      "volume": 778
    },
    {
      "date": "2016-10-01T00:00:00Z",
      "volume": 908
    },
    {
      "date": "2016-11-01T00:00:00Z",
      "volume": 713
    },
    {
      "date": "2016-12-01T00:00:00Z",
      "volume": 713
    },
    {
      "date": "2017-01-01T00:00:00Z",
      "volume": 1038
    },
    {
      "date": "2017-02-01T00:00:00Z",
      "volume": 1297
    },
    {
      "date": "2017-03-01T00:00:00Z",
      "volume": 1362
    },
    {
      "date": "2017-04-01T00:00:00Z",
      "volume": 908
    },
    {
      "date": "2017-05-01T00:00:00Z",
      "volume": 713
    },
    {
      "date": "2017-06-01T00:00:00Z",
      "volume": 389
    },
    {
      "date": "2017-07-01T00:00:00Z",
      "volume": 260
    },
    {
      "date": "2017-08-01T00:00:00Z",
      "volume": 519
    },
    {
      "date": "2017-09-01T00:00:00Z",
      "volume": 435
    },
    {
      "date": "2017-10-01T00:00:00Z",
      "volume": 513
    },
    {
      "date": "2017-11-01T00:00:00Z",
      "volume": 420
    },
    {
      "date": "2017-12-01T00:00:00Z",
      "volume": 433
    },
    {
      "date": "2018-01-01T00:00:00Z",
      "volume": 461
    },
    {
      "date": "2018-02-01T00:00:00Z",
      "volume": 369
    },
    {
      "date": "2018-03-01T00:00:00Z",
      "volume": 370
    },
    {
      "date": "2018-04-01T00:00:00Z",
      "volume": 318
    },
    {
      "date": "2018-05-01T00:00:00Z",
      "volume": 318
    },
    {
      "date": "2018-06-01T00:00:00Z",
      "volume": 357
    },
    {
      "date": "2018-07-01T00:00:00Z",
      "volume": 370
    },
    {
      "date": "2018-08-01T00:00:00Z",
      "volume": 409
    },
    {
      "date": "2018-09-01T00:00:00Z",
      "volume": 513
    },
    {
      "date": "2018-10-01T00:00:00Z",
      "volume": 603
    },
    {
      "date": "2018-11-01T00:00:00Z",
      "volume": 565
    },
    {
      "date": "2018-12-01T00:00:00Z",
      "volume": 422
    },
    {
      "date": "2019-01-01T00:00:00Z",
      "volume": 331
    },
    {
      "date": "2019-02-01T00:00:00Z",
      "volume": 383
    },
    {
      "date": "2019-03-01T00:00:00Z",
      "volume": 474
    },
    {
      "date": "2019-04-01T00:00:00Z",
      "volume": 552
    },
    {
      "date": "2019-05-01T00:00:00Z",
      "volume": 552
    },
    {
      "date": "2019-06-01T00:00:00Z",
      "volume": 526
    },
    {
      "date": "2019-07-01T00:00:00Z",
      "volume": 500
    },
    {
      "date": "2019-08-01T00:00:00Z",
      "volume": 474
    },
    {
      "date": "2019-09-01T00:00:00Z",
      "volume": 552
    },
    {
      "date": "2019-10-01T00:00:00Z",
      "volume": 630
    },
    {
      "date": "2019-11-01T00:00:00Z",
      "volume": 655
    },
    {
      "date": "2019-12-01T00:00:00Z",
      "volume": 701
    },
    {
      "date": "2020-01-01T00:00:00Z",
      "volume": 388
    },
    {
      "date": "2020-02-01T00:00:00Z",
      "volume": 419
    },
    {
      "date": "2020-03-01T00:00:00Z",
      "volume": 405
    },
    {
      "date": "2020-04-01T00:00:00Z",
      "volume": 475
    },
    {
      "date": "2020-05-01T00:00:00Z",
      "volume": 459
    },
    {
      "date": "2020-06-01T00:00:00Z",
      "volume": 481
    },
    {
      "date": "2020-07-01T00:00:00Z",
      "volume": 506
    },
    {
      "date": "2020-08-01T00:00:00Z",
      "volume": 487
    },
    {
      "date": "2020-09-01T00:00:00Z",
      "volume": 591
    },
    {
      "date": "2020-10-01T00:00:00Z",
      "volume": 502
    },
    {
      "date": "2020-11-01T00:00:00Z",
      "volume": 460
    },
    {
      "date": "2020-12-01T00:00:00Z",
      "volume": 438
    },
    {
      "date": "2021-01-01T00:00:00Z",
      "volume": 463
    },
    {
      "date": "2021-02-01T00:00:00Z",
      "volume": 487
    },
    {
      "date": "2021-03-01T00:00:00Z",
      "volume": 490
    },
    {
      "date": "2021-04-01T00:00:00Z",
      "volume": 459
    },
    {
      "date": "2021-05-01T00:00:00Z",
      "volume": 426
    },
    {
      "date": "2021-06-01T00:00:00Z",
      "volume": 505
    },
    {
      "date": "2021-07-01T00:00:00Z",
      "volume": 491
    },
    {
      "date": "2021-08-01T00:00:00Z",
      "volume": 486
    },
    {
      "date": "2021-09-01T00:00:00Z",
      "volume": 552
    },
    {
      "date": "2021-10-01T00:00:00Z",
      "volume": 477
    },
    {
      "date": "2021-11-01T00:00:00Z",
      "volume": 438
    },
    {
      "date": "2021-12-01T00:00:00Z",
      "volume": 398
    },
    {
      "date": "2022-01-01T00:00:00Z",
      "volume": 416
    },
    {
      "date": "2022-02-01T00:00:00Z",
      "volume": 420
    },
    {
      "date": "2022-03-01T00:00:00Z",
      "volume": 433
    },
    {
      "date": "2022-04-01T00:00:00Z",
      "volume": 421
    },
    {
      "date": "2022-05-01T00:00:00Z",
      "volume": 397
    },
    {
      "date": "2022-06-01T00:00:00Z",
      "volume": 481
    },
    {
      "date": "2022-07-01T00:00:00Z",
      "volume": 477
    },
    {
      "date": "2022-08-01T00:00:00Z",
      "volume": 483
    },
    {
      "date": "2022-09-01T00:00:00Z",
      "volume": 562
    },
    {
      "date": "2022-10-01T00:00:00Z",
      "volume": 531
    },
    {
      "date": "2022-11-01T00:00:00Z",
      "volume": 409
    },
    {
      "date": "2022-12-01T00:00:00Z",
      "volume": 418
    },
    {
      "date": "2023-01-01T00:00:00Z",
      "volume": 443
    },
    {
      "date": "2023-02-01T00:00:00Z",
      "volume": 474
    },
    {
      "date": "2023-03-01T00:00:00Z",
      "volume": 515
    },
    {
      "date": "2023-04-01T00:00:00Z",
      "volume": 432
    },
    {
      "date": "2023-05-01T00:00:00Z",
      "volume": 513
    },
    {
      "date": "2023-06-01T00:00:00Z",
      "volume": 484
    },
    {
      "date": "2023-07-01T00:00:00Z",
      "volume": 470
    },
    {
      "date": "2023-08-01T00:00:00Z",
      "volume": 499
    },
    {
      "date": "2023-09-01T00:00:00Z",
      "volume": 556
    },
    {
      "date": "2023-10-01T00:00:00Z",
      "volume": 535
    },
    {
      "date": "2023-11-01T00:00:00Z",
      "volume": 463
    },
    {
      "date": "2023-12-01T00:00:00Z",
      "volume": 383
    },
    {
      "date": "2024-01-01T00:00:00Z",
      "volume": 512
    },
    {
      "date": "2024-02-01T00:00:00Z",
      "volume": 502
    },
    {
      "date": "2024-03-01T00:00:00Z",
      "volume": 461
    },
    {
      "date": "2024-04-01T00:00:00Z",
      "volume": 474
    },
    {
      "date": "2024-05-01T00:00:00Z",
      "volume": 484
    },
    {
      "date": "2024-06-01T00:00:00Z",
      "volume": 446
    },
    {
      "date": "2024-07-01T00:00:00Z",
      "volume": 447
    },
    {
      "date": "2024-08-01T00:00:00Z",
      "volume": 448
    },
    {
      "date": "2024-09-01T00:00:00Z",
      "volume": 451
    },
    {
      "date": "2024-10-01T00:00:00Z",
      "volume": 471
    },
    {
      "date": "2024-11-01T00:00:00Z",
      "volume": 447
    },
    {
      "date": "2024-12-01T00:00:00Z",
      "volume": 446
    },
    {
      "date": "2025-01-01T00:00:00Z",
      "volume": 445
    },
    {
      "date": "2025-02-01T00:00:00Z",
      "volume": 447
    },
    {
      "date": "2025-03-01T00:00:00Z",
      "volume": 556
    },
    {
      "date": "2025-04-01T00:00:00Z",
      "volume": 449
    },
    {
      "date": "2025-05-01T00:00:00Z",
      "volume": 450
    },
    {
      "date": "2025-06-01T00:00:00Z",
      "volume": 444
    },
    {
      "date": "2025-07-01T00:00:00Z",
      "volume": 417
    },
    {
      "date": "2025-08-01T00:00:00Z",
      "volume": 468
    },
    {
      "date": "2025-09-01T00:00:00Z",
      "volume": 533
    },
    {
      "date": "2025-10-01T00:00:00Z",
      "volume": 525
    },
    {
      "date": "2025-11-01T00:00:00Z",
      "volume": 454
    },
    {
      "date": "2025-12-01T00:00:00Z",
      "volume": 411
    }
  ]
}
