{
  "keyword": "Magnesium Gluconate",
  "country": "us",
  "fetchedAt": "2025-09-27T02:59:13.970Z",
  "metrics": [
    {
      "date": "2016-01-01T00:00:00Z",
      "volume": 2829
    },
    {
      "date": "2016-02-01T00:00:00Z",
      "volume": 2766
    },
    {
      "date": "2016-03-01T00:00:00Z",
      "volume": 3044
    },
    {
      "date": "2016-04-01T00:00:00Z",
      "volume": 3106
    },
    {
      "date": "2016-05-01T00:00:00Z",
      "volume": 2790
    },
    {
      "date": "2016-06-01T00:00:00Z",
      "volume": 2962
    },
    {
      "date": "2016-07-01T00:00:00Z",
      "volume": 2351
    },
    {
      "date": "2016-08-01T00:00:00Z",
      "volume": 2473
    },
    {
      "date": "2016-09-01T00:00:00Z",
      "volume": 3174
    },
    {
      "date": "2016-10-01T00:00:00Z",
      "volume": 2629
    },
    {
      "date": "2016-11-01T00:00:00Z",
      "volume": 2598
    },
    {
      "date": "2016-12-01T00:00:00Z",
      "volume": 1376
    },
    {
      "date": "2017-01-01T00:00:00Z",
      "volume": 2566
    },
    {
      "date": "2017-02-01T00:00:00Z",
      "volume": 2860
    },
    {
      "date": "2017-03-01T00:00:00Z",
      "volume": 3384
    },
    {
      "date": "2017-04-01T00:00:00Z",
      "volume": 3364
    },
    {
      "date": "2017-05-01T00:00:00Z",
      "volume": 3260
    },
    {
      "date": "2017-06-01T00:00:00Z",
      "volume": 3037
    },
    {
      "date": "2017-07-01T00:00:00Z",
      "volume": 2642
    },
    {
      "date": "2017-08-01T00:00:00Z",
      "volume": 2722
    },
    {
      "date": "2017-09-01T00:00:00Z",
      "volume": 3078
    },
    {
      "date": "2017-10-01T00:00:00Z",
      "volume": 3675
    },
    {
      "date": "2017-11-01T00:00:00Z",
      "volume": 3493
    },
    {
      "date": "2017-12-01T00:00:00Z",
      "volume": 3195
    },
    {
      "date": "2018-01-01T00:00:00Z",
      "volume": 3294
    },
    {
      "date": "2018-02-01T00:00:00Z",
      "volume": 3460
    },
    {
      "date": "2018-03-01T00:00:00Z",
      "volume": 3738
    },
    {
      "date": "2018-04-01T00:00:00Z",
      "volume": 3829
    },
    {
      "date": "2018-05-01T00:00:00Z",
      "volume": 3613
    },
    {
      "date": "2018-06-01T00:00:00Z",
      "volume": 3506
    },
    {
      "date": "2018-07-01T00:00:00Z",
      "volume": 3083
    },
    {
      "date": "2018-08-01T00:00:00Z",
      "volume": 3348
    },
    {
      "date": "2018-09-01T00:00:00Z",
      "volume": 3158
    },
    {
      "date": "2018-10-01T00:00:00Z",
      "volume": 4153
    },
    {
      "date": "2018-11-01T00:00:00Z",
      "volume": 3932
    },
    {
      "date": "2018-12-01T00:00:00Z",
      "volume": 3423
    },
    {
      "date": "2019-01-01T00:00:00Z",
      "volume": 3816
    },
    {
      "date": "2019-02-01T00:00:00Z",
      "volume": 3865
    },
    {
      "date": "2019-03-01T00:00:00Z",
      "volume": 2324
    },
    {
      "date": "2019-04-01T00:00:00Z",
      "volume": 3252
    },
    {
      "date": "2019-05-01T00:00:00Z",
      "volume": 3888
    },
    {
      "date": "2019-06-01T00:00:00Z",
      "volume": 3371
    },
    {
      "date": "2019-07-01T00:00:00Z",
      "volume": 3678
    },
    {
      "date": "2019-08-01T00:00:00Z",
      "volume": 3930
    },
    {
      "date": "2019-09-01T00:00:00Z",
      "volume": 4652
    },
    {
      "date": "2019-10-01T00:00:00Z",
      "volume": 3788
    },
    {
      "date": "2019-11-01T00:00:00Z",
      "volume": 3066
    },
    {
      "date": "2019-12-01T00:00:00Z",
      "volume": 2701
    },
    {
      "date": "2020-01-01T00:00:00Z",
      "volume": 4074
    },
    {
      "date": "2020-02-01T00:00:00Z",
      "volume": 3621
    },
    {
      "date": "2020-03-01T00:00:00Z",
      "volume": 3371
    },
    {
      "date": "2020-04-01T00:00:00Z",
      "volume": 2998
    },
    {
      "date": "2020-05-01T00:00:00Z",
      "volume": 3100
    },
    {
      "date": "2020-06-01T00:00:00Z",
      "volume": 2999
    },
    {
      "date": "2020-07-01T00:00:00Z",
      "volume": 3417
    },
    {
      "date": "2020-08-01T00:00:00Z",
      "volume": 4437
    },
    {
      "date": "2020-09-01T00:00:00Z",
      "volume": 3462
    },
    {
      "date": "2020-10-01T00:00:00Z",
      "volume": 3916
    },
    {
      "date": "2020-11-01T00:00:00Z",
      "volume": 2882
    },
    {
      "date": "2020-12-01T00:00:00Z",
      "volume": 2644
    },
    {
      "date": "2021-01-01T00:00:00Z",
      "volume": 3804
    },
    {
      "date": "2021-02-01T00:00:00Z",
      "volume": 2936
    },
    {
      "date": "2021-03-01T00:00:00Z",
      "volume": 3359
    },
    {
      "date": "2021-04-01T00:00:00Z",
      "volume": 3742
    },
    {
      "date": "2021-05-01T00:00:00Z",
      "volume": 3634
    },
    {
      "date": "2021-06-01T00:00:00Z",
      "volume": 2655
    },
    {
      "date": "2021-07-01T00:00:00Z",
      "volume": 3179
    },
    {
      "date": "2021-08-01T00:00:00Z",
      "volume": 3678
    },
    {
      "date": "2021-09-01T00:00:00Z",
      "volume": 3284
    },
    {
      "date": "2021-10-01T00:00:00Z",
      "volume": 3518
    },
    {
      "date": "2021-11-01T00:00:00Z",
      "volume": 2881
    },
    {
      "date": "2021-12-01T00:00:00Z",
      "volume": 2878
    },
    {
      "date": "2022-01-01T00:00:00Z",
      "volume": 3794
    },
    {
      "date": "2022-02-01T00:00:00Z",
      "volume": 5668
    },
    {
      "date": "2022-03-01T00:00:00Z",
      "volume": 4752
    },
    {
      "date": "2022-04-01T00:00:00Z",
      "volume": 4027
    },
    {
      "date": "2022-05-01T00:00:00Z",
      "volume": 3971
    },
    {
      "date": "2022-06-01T00:00:00Z",
      "volume": 4024
    },
    {
      "date": "2022-07-01T00:00:00Z",
      "volume": 5007
    },
    {
      "date": "2022-08-01T00:00:00Z",
      "volume": 4222
    },
    {
      "date": "2022-09-01T00:00:00Z",
      "volume": 4828
    },
    {
      "date": "2022-10-01T00:00:00Z",
      "volume": 4462
    },
    {
      "date": "2022-11-01T00:00:00Z",
      "volume": 3846
    },
    {
      "date": "2022-12-01T00:00:00Z",
      "volume": 4305
    },
    {
      "date": "2023-01-01T00:00:00Z",
      "volume": 5412
    },
    {
      "date": "2023-02-01T00:00:00Z",
      "volume": 6774
    },
    {
      "date": "2023-03-01T00:00:00Z",
      "volume": 5787
    },
    {
      "date": "2023-04-01T00:00:00Z",
      "volume": 5919
    },
    {
      "date": "2023-05-01T00:00:00Z",
      "volume": 5683
    },
    {
      "date": "2023-06-01T00:00:00Z",
      "volume": 6793
    },
    {
      "date": "2023-07-01T00:00:00Z",
      "volume": 5336
    },
    {
      "date": "2023-08-01T00:00:00Z",
      "volume": 6290
    },
    {
      "date": "2023-09-01T00:00:00Z",
      "volume": 6768
    },
    {
      "date": "2023-10-01T00:00:00Z",
      "volume": 6226
    },
    {
      "date": "2023-11-01T00:00:00Z",
      "volume": 5695
    },
    {
      "date": "2023-12-01T00:00:00Z",
      "volume": 4907
    },
    {
      "date": "2024-01-01T00:00:00Z",
      "volume": 6497
    },
    {
      "date": "2024-02-01T00:00:00Z",
      "volume": 6628
    },
    {
      "date": "2024-03-01T00:00:00Z",
      "volume": 6313
    },
    {
      "date": "2024-04-01T00:00:00Z",
      "volume": 6378
    },
    {
      "date": "2024-05-01T00:00:00Z",
      "volume": 6356
    },
    {
      "date": "2024-06-01T00:00:00Z",
      "volume": 6303
    },
    {
      "date": "2024-07-01T00:00:00Z",
      "volume": 6235
    },
    {
      "date": "2024-08-01T00:00:00Z",
      "volume": 6526
    },
    {
      "date": "2024-09-01T00:00:00Z",
      "volume": 6665
    },
    {
      "date": "2024-10-01T00:00:00Z",
      "volume": 6705
    },
    {
      "date": "2024-11-01T00:00:00Z",
      "volume": 6271
    },
    {
      "date": "2024-12-01T00:00:00Z",
      "volume": 5948
    },
    {
      "date": "2025-01-01T00:00:00Z",
      "volume": 6838
    },
    {
      "date": "2025-02-01T00:00:00Z",
      "volume": 7176
    },
    {
      "date": "2025-03-01T00:00:00Z",
      "volume": 6855
    },
    {
      "date": "2025-04-01T00:00:00Z",
      "volume": 6927
    },
    {
      "date": "2025-05-01T00:00:00Z",
      "volume": 6908
    },
    {
      "date": "2025-06-01T00:00:00Z",
      "volume": 6859
    },
    {
      "date": "2025-07-01T00:00:00Z",
      "volume": 6795
    },
    {
      "date": "2025-08-01T00:00:00Z",
      "volume": 7090
    },
    {
      "date": "2025-09-01T00:00:00Z",
      "volume": 7232
    },
    {
      "date": "2025-10-01T00:00:00Z",
      "volume": 7277
    },
    {
      "date": "2025-11-01T00:00:00Z",
      "volume": 6847
    },
    {
      "date": "2025-12-01T00:00:00Z",
      "volume": 6527
    }
  ]
}
